{
  "MachineURL": "HoS/YotB",
  "Name": "Year of the Blight",
  "Version": "1.0.3",
  "ModListHash": "K89Td0OYAXU=",
  "Archives": [
    {
      "Status": "Valid",
      "Original": {
        "Hash": "RL9TEoqW6wY=",
        "Meta": "[General]\ndirectURL=https://github.com/ModOrganizer2/modorganizer/releases/download/v2.5.0/Mod.Organizer-2.5.0.7z",
        "Name": "Mod.Organizer-2.5.0_5e851380186453bbe8bf61357ae84d87fcc79e9f5d76e1af3901017538ef89e8_.7z",
        "Size": 138186906,
        "State": {
          "$type": "HttpDownloader, Wabbajack.Lib",
          "Headers": [],
          "Url": "https://github.com/ModOrganizer2/modorganizer/releases/download/v2.5.0/Mod.Organizer-2.5.0.7z"
        }
      }
    },
    {
      "Status": "Valid",
      "Original": {
        "Hash": "6PQD1rvvWI4=",
        "Meta": "[General]\ngameName=dragonage\nmodID=3257\nfileID=16760",
        "Name": "Armored Ogres of Ferelden-3257-1-0.zip",
        "Size": 7101378,
        "State": {
          "$type": "NexusDownloader, Wabbajack.Lib",
          "Author": "NeoKingArthur",
          "Description": "This mod will replace some/most/all ogres in Dragon Age Origins into their armored variant from Dragon Age: Awakening.",
          "FileID": 16760,
          "GameName": "DragonAgeOrigins",
          "ImageURL": "https://staticdelivery.nexusmods.com/mods/140/images/3257-1-1320413969.png",
          "IsNSFW": false,
          "ModID": 3257,
          "Name": "Armored Ogres of Ferelden",
          "Version": "1.0"
        }
      }
    },
    {
      "Status": "Valid",
      "Original": {
        "Hash": "wzHflB+soRE=",
        "Meta": "[General]\ngameName=dragonage\nmodID=4781\nfileID=1000005742",
        "Name": "Casteless Brand and Dwarven Tattoo Restoration-4781-2.7z",
        "Size": 163558,
        "State": {
          "$type": "NexusDownloader, Wabbajack.Lib",
          "Author": "skltra",
          "Description": "Adds casteless brand to the casteless dwarves without it. Restores missing tattoos to Oghren, Mischa, and Tug.",
          "FileID": 1000005742,
          "GameName": "DragonAgeOrigins",
          "ImageURL": "https://staticdelivery.nexusmods.com/mods/140/images/4781/4781-1520881908-1021747226.jpeg",
          "IsNSFW": false,
          "ModID": 4781,
          "Name": "Casteless Brand and Dwarven Tattoo Restoration",
          "Version": "2"
        }
      }
    },
    {
      "Status": "Valid",
      "Original": {
        "Hash": "Bf/6QErk2TE=",
        "Meta": "[General]\ngameName=dragonage\nmodID=5598\nfileID=1000008490",
        "Name": "DA2 Elves Triple Mix-5598-1-0-1636834752.rar",
        "Size": 6868648,
        "State": {
          "$type": "NexusDownloader, Wabbajack.Lib",
          "Author": "AzureWitch",
          "Description": "A new DA2 elves mod that mixes features of the other three existing mods. Requires only Elf Update.",
          "FileID": 1000008490,
          "GameName": "DragonAgeOrigins",
          "ImageURL": "https://staticdelivery.nexusmods.com/mods/140/images/5598/5598-1636833958-1240621150.png",
          "IsNSFW": false,
          "ModID": 5598,
          "Name": "DA2 Elves Triple Mix",
          "Version": "1.0"
        }
      }
    },
    {
      "Status": "Valid",
      "Original": {
        "Hash": "UwMm7DhTuMk=",
        "Meta": "[General]\ngameName=dragonage\nmodID=883\nfileID=18266",
        "Name": "DLC Fix Tool 1-14-883-1-14.zip",
        "Size": 1090,
        "State": {
          "$type": "NexusDownloader, Wabbajack.Lib",
          "Author": "Mad Method",
          "Description": "This tool patches all the DLC items so they transfer properly to Awakenings.",
          "FileID": 18266,
          "GameName": "DragonAgeOrigins",
          "ImageURL": "https://staticdelivery.nexusmods.com/mods/140/images/883-1-1269092763.png",
          "IsNSFW": false,
          "ModID": 883,
          "Name": "DLC Transfer To Awakening Patch",
          "Version": "1.14"
        }
      }
    },
    {
      "Status": "Valid",
      "Original": {
        "Hash": "Z1uuPW/cNB8=",
        "Meta": "[General]\ngameName=dragonage\nmodID=686\nfileID=1000008458",
        "Name": "Dragon Age Redesigned Manual Version 1.0-686-1-0-1635410667.zip",
        "Size": 84701491,
        "State": {
          "$type": "NexusDownloader, Wabbajack.Lib",
          "Author": "Dracomies",
          "Description": "This is the continuation of Dragon Age Redesigned. \n\n\n\nIf file is hidden, it is also here:\n\nhttp://social.bioware.com/project/1205/#files",
          "FileID": 1000008458,
          "GameName": "DragonAgeOrigins",
          "ImageURL": "https://staticdelivery.nexusmods.com/mods/140/images/686-1-1265178738.jpg",
          "IsNSFW": false,
          "ModID": 686,
          "Name": "Dragon Age Redesigned",
          "Version": "1.0"
        }
      }
    },
    {
      "Status": "Valid",
      "Original": {
        "Hash": "5V4YrO7peQU=",
        "Meta": "[General]\ngameName=dragonage\nmodID=3973\nfileID=1000003495",
        "Name": "Elelith_textures_DAO_Enviroment-3973-.7z",
        "Size": 409412148,
        "State": {
          "$type": "NexusDownloader, Wabbajack.Lib",
          "Author": "Elelith SplitCoreGaming",
          "Description": "Hated the ugly blotchy item textures so figured I\u0027d fix a couple, but the thing got a little out of hand. So I have been (very) slowly retexturing parts of the game.",
          "FileID": 1000003495,
          "GameName": "DragonAgeOrigins",
          "ImageURL": "https://staticdelivery.nexusmods.com/mods/140/images/3973-1-1384265299.jpg",
          "IsNSFW": false,
          "ModID": 3973,
          "Name": "Retexturing DAO",
          "Version": ""
        }
      }
    },
    {
      "Status": "Valid",
      "Original": {
        "Hash": "Vb813/5fv6M=",
        "Meta": "[General]\ngameName=dragonage\nmodID=5598\nfileID=1000009393",
        "Name": "Fixed DLC Morphs-5598-1-0-1666730323.rar",
        "Size": 748270,
        "State": {
          "$type": "NexusDownloader, Wabbajack.Lib",
          "Author": "AzureWitch",
          "Description": "A new DA2 elves mod that mixes features of the other three existing mods. Requires only Elf Update.",
          "FileID": 1000009393,
          "GameName": "DragonAgeOrigins",
          "ImageURL": "https://staticdelivery.nexusmods.com/mods/140/images/5598/5598-1636833958-1240621150.png",
          "IsNSFW": false,
          "ModID": 5598,
          "Name": "DA2 Elves Triple Mix",
          "Version": "1.0"
        }
      }
    },
    {
      "Status": "Valid",
      "Original": {
        "Hash": "Reax3fhHA6M=",
        "Meta": "[General]\ngameName=dragonage\nmodID=882\nfileID=4435",
        "Name": "Gift Guide - Awakening-882.zip",
        "Size": 49733,
        "State": {
          "$type": "NexusDownloader, Wabbajack.Lib",
          "Author": "hdhd",
          "Description": "Adds gift descriptions for Dragon Age: Awakening, The Stone Prisoner and Return to Ostagar.",
          "FileID": 4435,
          "GameName": "DragonAgeOrigins",
          "ImageURL": "https://staticdelivery.nexusmods.com/mods/140/images/882-1-1268942917.jpg",
          "IsNSFW": false,
          "ModID": 882,
          "Name": "Gift Guide - Awakening",
          "Version": "1.2"
        }
      }
    },
    {
      "Status": "Valid",
      "Original": {
        "Hash": "//RiboP+qXw=",
        "Meta": "[General]\ngameName=dragonage\nmodID=3258\nfileID=17152",
        "Name": "Main File - Grey Wardens of Ferelden-3258-2-5.zip",
        "Size": 378248,
        "State": {
          "$type": "NexusDownloader, Wabbajack.Lib",
          "Author": "NeoKingArthur",
          "Description": "This mod will give you DA2 style Grey Warden armors and weapons for DA:O. This mod also changes the appearances of all Grey Warden NPCs into wearing a uniform Grey Warden armors.",
          "FileID": 17152,
          "GameName": "DragonAgeOrigins",
          "ImageURL": "https://staticdelivery.nexusmods.com/mods/140/images/3258-1-1323317032.png",
          "IsNSFW": false,
          "ModID": 3258,
          "Name": "Grey Wardens of Ferelden",
          "Version": "2.5"
        }
      }
    },
    {
      "Status": "Valid",
      "Original": {
        "Hash": "T8ZdFl8kbsk=",
        "Meta": "[General]\ngameName=dragonage\nmodID=15\nfileID=11654",
        "Name": "JB3narmor-15.7z",
        "Size": 278757288,
        "State": {
          "$type": "NexusDownloader, Wabbajack.Lib",
          "Author": "reative",
          "Description": "Much better and sharpen textures!",
          "FileID": 11654,
          "GameName": "DragonAgeOrigins",
          "ImageURL": "https://staticdelivery.nexusmods.com/mods/140/images/15-1-1300115348.jpg",
          "IsNSFW": false,
          "ModID": 15,
          "Name": "JB3textures",
          "Version": "3.1"
        }
      }
    },
    {
      "Status": "Valid",
      "Original": {
        "Hash": "tptGLVuJk0E=",
        "Meta": "[General]\ngameName=dragonage\nmodID=4462\nfileID=1000003568",
        "Name": "JB3narmor-4462-1-1.zip",
        "Size": 41198668,
        "State": {
          "$type": "NexusDownloader, Wabbajack.Lib",
          "Author": "magpiedragon",
          "Description": "Replaces vanilla meshes for Medium and Heavy female armors for all races with more unisex ones. Includes edited armor textures to match. No more boobplate.",
          "FileID": 1000003568,
          "GameName": "DragonAgeOrigins",
          "ImageURL": "https://staticdelivery.nexusmods.com/mods/140/images/4462-0-1462355101.jpg",
          "IsNSFW": false,
          "ModID": 4462,
          "Name": "Neutral Female Armor (Medium and Heavy edition)",
          "Version": "1.1"
        }
      }
    },
    {
      "Status": "Valid",
      "Original": {
        "Hash": "49NttKgGIAg=",
        "Meta": "[General]\ngameName=dragonage\nmodID=15\nfileID=11681",
        "Name": "JB3ncreatures-15.7z",
        "Size": 222400517,
        "State": {
          "$type": "NexusDownloader, Wabbajack.Lib",
          "Author": "reative",
          "Description": "Much better and sharpen textures!",
          "FileID": 11681,
          "GameName": "DragonAgeOrigins",
          "ImageURL": "https://staticdelivery.nexusmods.com/mods/140/images/15-1-1300115348.jpg",
          "IsNSFW": false,
          "ModID": 15,
          "Name": "JB3textures",
          "Version": "3.1"
        }
      }
    },
    {
      "Status": "Valid",
      "Original": {
        "Hash": "zvyhYF31eh4=",
        "Meta": "[General]\ngameName=dragonage\nmodID=15\nfileID=11524",
        "Name": "JB3nenvironment-15.7z",
        "Size": 161114795,
        "State": {
          "$type": "NexusDownloader, Wabbajack.Lib",
          "Author": "reative",
          "Description": "Much better and sharpen textures!",
          "FileID": 11524,
          "GameName": "DragonAgeOrigins",
          "ImageURL": "https://staticdelivery.nexusmods.com/mods/140/images/15-1-1300115348.jpg",
          "IsNSFW": false,
          "ModID": 15,
          "Name": "JB3textures",
          "Version": "3.1"
        }
      }
    },
    {
      "Status": "Valid",
      "Original": {
        "Hash": "cdWCVivwSo8=",
        "Meta": "[General]\ngameName=dragonage\nmodID=15\nfileID=11464",
        "Name": "JB3nprops-15.7z",
        "Size": 94323283,
        "State": {
          "$type": "NexusDownloader, Wabbajack.Lib",
          "Author": "reative",
          "Description": "Much better and sharpen textures!",
          "FileID": 11464,
          "GameName": "DragonAgeOrigins",
          "ImageURL": "https://staticdelivery.nexusmods.com/mods/140/images/15-1-1300115348.jpg",
          "IsNSFW": false,
          "ModID": 15,
          "Name": "JB3textures",
          "Version": "3.1"
        }
      }
    },
    {
      "Status": "Valid",
      "Original": {
        "Hash": "ZSYo8+u2Bys=",
        "Meta": "[General]\ngameName=dragonage\nmodID=15\nfileID=1000000589",
        "Name": "TEST-15-.7z",
        "Size": 664218692,
        "State": {
          "$type": "NexusDownloader, Wabbajack.Lib",
          "Author": "reative",
          "Description": "Much better and sharpen textures!",
          "FileID": 1000000589,
          "GameName": "DragonAgeOrigins",
          "ImageURL": "https://staticdelivery.nexusmods.com/mods/140/images/15-1-1300115348.jpg",
          "IsNSFW": false,
          "ModID": 15,
          "Name": "JB3textures",
          "Version": "3.1"
        }
      }
    },
    {
      "Status": "Valid",
      "Original": {
        "Hash": "6sGiokF98PM=",
        "Meta": "[General]\ngameName=dragonage\nmodID=385\nfileID=1579",
        "Name": "Madd Gift Guide V1_1-385.zip",
        "Size": 86492,
        "State": {
          "$type": "NexusDownloader, Wabbajack.Lib",
          "Author": "MaddBomber83",
          "Description": "Item Descriptions for Gifts",
          "FileID": 1579,
          "GameName": "DragonAgeOrigins",
          "ImageURL": "https://staticdelivery.nexusmods.com/mods/140/images/385-1-1261258879.jpg",
          "IsNSFW": false,
          "ModID": 385,
          "Name": "Madd Gift Guide",
          "Version": "1.1"
        }
      }
    },
    {
      "Status": "Valid",
      "Original": {
        "Hash": "k930H8GPexg=",
        "Meta": "[General]\ngameName=dragonage\nmodID=3253\nfileID=16748",
        "Name": "Mages of Ferelden-3253-1-0.zip",
        "Size": 179779,
        "State": {
          "$type": "NexusDownloader, Wabbajack.Lib",
          "Author": "NeoKingArthur",
          "Description": "This mod will change the appearance of all Circle Mage Robes from the weird looking model into the clean more elegant model of First Enchanter Irving\u0027s robe style.",
          "FileID": 16748,
          "GameName": "DragonAgeOrigins",
          "ImageURL": "https://staticdelivery.nexusmods.com/mods/140/images/3253-1-1323318200.png",
          "IsNSFW": false,
          "ModID": 3253,
          "Name": "Mages of Ferelden",
          "Version": "1.0"
        }
      }
    },
    {
      "Status": "Valid",
      "Original": {
        "Hash": "YQaNxEFhdkw=",
        "Meta": "[General]\ngameName=dragonage\nmodID=3973\nfileID=1000003494",
        "Name": "Elelith_textures_DAO-3973-.7z",
        "Size": 163178776,
        "State": {
          "$type": "NexusDownloader, Wabbajack.Lib",
          "Author": "Elelith SplitCoreGaming",
          "Description": "Hated the ugly blotchy item textures so figured I\u0027d fix a couple, but the thing got a little out of hand. So I have been (very) slowly retexturing parts of the game.",
          "FileID": 1000003494,
          "GameName": "DragonAgeOrigins",
          "ImageURL": "https://staticdelivery.nexusmods.com/mods/140/images/3973-1-1384265299.jpg",
          "IsNSFW": false,
          "ModID": 3973,
          "Name": "Retexturing DAO",
          "Version": ""
        }
      }
    },
    {
      "Status": "Valid",
      "Original": {
        "Hash": "/j16uNTsKLU=",
        "Meta": "[General]\ngameName=dragonage\nmodID=5019\nfileID=1000006185",
        "Name": "Revised Tattoos - Complete Pack-5019-V1-1550694987.zip",
        "Size": 3733978,
        "State": {
          "$type": "NexusDownloader, Wabbajack.Lib",
          "Author": "tepkunset",
          "Description": "Unique, human, dwarf and Dalish tattoos (vallaslin) redrawn by hand with a higher resolution, stronger colour, sharper designs and a few other small tweaks. All together in one download now.",
          "FileID": 1000006185,
          "GameName": "DragonAgeOrigins",
          "ImageURL": "https://staticdelivery.nexusmods.com/mods/140/images/5019/5019-1550694530-787600770.png",
          "IsNSFW": false,
          "ModID": 5019,
          "Name": "Revised Tattoos (Complete Pack)",
          "Version": "V1"
        }
      }
    },
    {
      "Status": "Valid",
      "Original": {
        "Hash": "ILeRTUzPjhg=",
        "Meta": "[General]\ngameName=dragonage\nmodID=4597\nfileID=1000004271",
        "Name": "SJC\u0027s Skins-4597-.zip",
        "Size": 203240538,
        "State": {
          "$type": "NexusDownloader, Wabbajack.Lib",
          "Author": "SammyJC",
          "Description": "12 additional skins for character creation.",
          "FileID": 1000004271,
          "GameName": "DragonAgeOrigins",
          "ImageURL": "https://staticdelivery.nexusmods.com/mods/140/images/4597-0-1482263821.png",
          "IsNSFW": false,
          "ModID": 4597,
          "Name": "SJC\u0027s Skins",
          "Version": ""
        }
      }
    },
    {
      "Status": "Valid",
      "Original": {
        "Hash": "GGAOuf/cCv8=",
        "Meta": "[General]\ngameName=dragonage\nmodID=4400\nfileID=1000003239",
        "Name": "Sten of the Beresaad-4400-.7z",
        "Size": 749700,
        "State": {
          "$type": "NexusDownloader, Wabbajack.Lib",
          "Author": "untamedfuture",
          "Description": "Unique head mesh and morph for Sten, to be used with updated Qunari mod.",
          "FileID": 1000003239,
          "GameName": "DragonAgeOrigins",
          "ImageURL": "https://staticdelivery.nexusmods.com/mods/140/images/4400-5-1452060749.jpg",
          "IsNSFW": false,
          "ModID": 4400,
          "Name": "Sten of the Beresaad",
          "Version": ""
        }
      }
    },
    {
      "Status": "Valid",
      "Original": {
        "Hash": "fhbjwu1XaNw=",
        "Meta": "[General]\ngameName=dragonage\nmodID=3256\nfileID=16865",
        "Name": "Templars of Ferelden-3256-1-0.zip",
        "Size": 247458,
        "State": {
          "$type": "NexusDownloader, Wabbajack.Lib",
          "Author": "NeoKingArthur",
          "Description": "This mod will replace all of the templar armors in Dragon Age: Origins into Dragon Age 2 templar armor designs.",
          "FileID": 16865,
          "GameName": "DragonAgeOrigins",
          "ImageURL": "https://staticdelivery.nexusmods.com/mods/140/images/3256-1-1323318940.png",
          "IsNSFW": false,
          "ModID": 3256,
          "Name": "Templars of Ferelden - Armors",
          "Version": "1.0"
        }
      }
    },
    {
      "Status": "Valid",
      "Original": {
        "Hash": "K4j5g90GDSw=",
        "Meta": "[General]\ngameName=dragonage\nmodID=3869\nfileID=1000000997",
        "Name": "Theta HD 1_2-3869-1-2.zip",
        "Size": 21544250,
        "State": {
          "$type": "NexusDownloader, Wabbajack.Lib",
          "Author": "Rennn",
          "Description": "A project to enhance Dragon Age\\\u0027s worst textures, and to fix graphical inconsistencies, without hurting performance or consuming excess RAM or VRAM.",
          "FileID": 1000000997,
          "GameName": "DragonAgeOrigins",
          "ImageURL": "https://staticdelivery.nexusmods.com/mods/140/images/3869-2-1377829513.jpg",
          "IsNSFW": false,
          "ModID": 3869,
          "Name": "Theta HD",
          "Version": "1.2"
        }
      }
    },
    {
      "Status": "Valid",
      "Original": {
        "Hash": "nwvoT1aNWQ4=",
        "Meta": "[General]\ngameName=dragonage\nmodID=6216\nfileID=1000011013",
        "Name": "Theta HD Fix (complete pack) 1.3-6216-1-3-1702469063.7z",
        "Size": 14177017,
        "State": {
          "$type": "NexusDownloader, Wabbajack.Lib",
          "Author": "gioveb",
          "Description": "Fixes some textures from Theta HD mod. The original mod is not strictly required.",
          "FileID": 1000011013,
          "GameName": "DragonAgeOrigins",
          "ImageURL": "https://staticdelivery.nexusmods.com/mods/140/images/6216/6216-1698270463-152976401.png",
          "IsNSFW": false,
          "ModID": 6216,
          "Name": "Theta HD (Fix)",
          "Version": "1.3"
        }
      }
    },
    {
      "Status": "Valid",
      "Original": {
        "Hash": "r9dPAMhxVVU=",
        "Meta": "[General]\ngameName=dragonage\nmodID=4505\nfileID=1000003881",
        "Name": "Tranquil Brand-4505-v1.zip",
        "Size": 246973,
        "State": {
          "$type": "NexusDownloader, Wabbajack.Lib",
          "Author": "tepkunset",
          "Description": "Gives Tranquil NPCs the familiar brand from later games (specifically the DA:I design)",
          "FileID": 1000003881,
          "GameName": "DragonAgeOrigins",
          "ImageURL": "https://staticdelivery.nexusmods.com/mods/140/images/4505/4505-1519498770-995414108.jpeg",
          "IsNSFW": false,
          "ModID": 4505,
          "Name": "Tranquil Brand 2.0",
          "Version": "V2"
        }
      }
    },
    {
      "Status": "Valid",
      "Original": {
        "Hash": "z1qcvvPuWbY=",
        "Meta": "[General]\ngameName=dragonage\nmodID=5558\nfileID=1000008393",
        "Name": "Window of the Soul - Eyes replacement-5558-1-4-1632136555.rar",
        "Size": 934005,
        "State": {
          "$type": "NexusDownloader, Wabbajack.Lib",
          "Author": "Laast",
          "Description": "Eyes default replacement textures \u0026amp; tints for Vanilla \u002B Dragon Age Redesigned and/or Dracomies True Textures. Also supports Unique Face Textures for Companions DAO Edition mod.",
          "FileID": 1000008393,
          "GameName": "DragonAgeOrigins",
          "ImageURL": "https://staticdelivery.nexusmods.com/mods/140/images/5558/5558-1631394703-1937362585.jpeg",
          "IsNSFW": false,
          "ModID": 5558,
          "Name": "Window of the Soul - Eyes replacement",
          "Version": "1.4"
        }
      }
    },
    {
      "Status": "Valid",
      "Original": {
        "Hash": "BQ1R01uexrU=",
        "Meta": "[General]\ngameName=dragonage\nmodID=4393\nfileID=1000003145",
        "Name": "DP_DAO_Additional_Kid_Clothing-4393-1-1.7z",
        "Size": 1496755,
        "State": {
          "$type": "NexusDownloader, Wabbajack.Lib",
          "Author": "DarthParametric",
          "Description": "Adds scaled clothes models to fit kids, including commoner and noble clothes, mage robes, and medium armour. A resource pack for modders.",
          "FileID": 1000003145,
          "GameName": "DragonAgeOrigins",
          "ImageURL": "https://staticdelivery.nexusmods.com/mods/140/images/4393-5-1450535385.jpg",
          "IsNSFW": false,
          "ModID": 4393,
          "Name": "Additional Clothing for Kids (Mod Resource)",
          "Version": "1.1"
        }
      }
    },
    {
      "Status": "Valid",
      "Original": {
        "Hash": "IKloex+vc8Y=",
        "Meta": "[General]\ngameName=dragonage\nmodID=3255\nfileID=16754",
        "Name": "Chantry of Ferelden-3255-1-0.zip",
        "Size": 127769,
        "State": {
          "$type": "NexusDownloader, Wabbajack.Lib",
          "Author": "NeoKingArthur",
          "Description": "This mod will change all appearances of the Chantry robes into the Dragon Age 2 style. Requires Kirkwall Exports by Amycus.",
          "FileID": 16754,
          "GameName": "DragonAgeOrigins",
          "ImageURL": "https://staticdelivery.nexusmods.com/mods/140/images/3255-1-1323319034.png",
          "IsNSFW": false,
          "ModID": 3255,
          "Name": "Chantry of Ferelden - Robes",
          "Version": "1.0"
        }
      }
    },
    {
      "Status": "InValid",
      "Original": {
        "Hash": "8C0jlkeKVZg=",
        "Meta": "[General]\ndirectURL=https://www.moddb.com/downloads/start/110415",
        "Name": "da2_armour-light.zip",
        "Size": 7442537,
        "State": {
          "$type": "ModDBDownloader, Wabbajack.Lib",
          "Url": "https://www.moddb.com/downloads/start/110415"
        }
      }
    },
    {
      "Status": "Valid",
      "Original": {
        "Hash": "sis1UrfxWL4=",
        "Meta": "[General]\ngameName=dragonage\nmodID=5382\nfileID=1000007577",
        "Name": "More Hairs for Kids-5382-1-1-1607669535.7z",
        "Size": 1919867,
        "State": {
          "$type": "NexusDownloader, Wabbajack.Lib",
          "Author": "Shanamah",
          "Description": "A collection of vanilla hair conversions for kids, and a bunch of morphs that use them.",
          "FileID": 1000007577,
          "GameName": "DragonAgeOrigins",
          "ImageURL": "https://staticdelivery.nexusmods.com/mods/140/images/5382/5382-1607157084-805468054.png",
          "IsNSFW": false,
          "ModID": 5382,
          "Name": "More Hairs for Kids and Diversified Children",
          "Version": "1.1"
        }
      }
    },
    {
      "Status": "Valid",
      "Original": {
        "Hash": "gi+FmPBP5fQ=",
        "Meta": "[General]\ngameName=dragonage\nmodID=4462\nfileID=1000003569",
        "Name": "NEUTRAL FEMALE ARMOR (Medium and High edition)-4462-1-1.zip",
        "Size": 20138551,
        "State": {
          "$type": "NexusDownloader, Wabbajack.Lib",
          "Author": "magpiedragon",
          "Description": "Replaces vanilla meshes for Medium and Heavy female armors for all races with more unisex ones. Includes edited armor textures to match. No more boobplate.",
          "FileID": 1000003569,
          "GameName": "DragonAgeOrigins",
          "ImageURL": "https://staticdelivery.nexusmods.com/mods/140/images/4462-0-1462355101.jpg",
          "IsNSFW": false,
          "ModID": 4462,
          "Name": "Neutral Female Armor (Medium and Heavy edition)",
          "Version": "1.1"
        }
      }
    },
    {
      "Status": "Valid",
      "Original": {
        "Hash": "nOiVzkHlOuw=",
        "Meta": "[General]\ngameName=dragonage\nmodID=4559\nfileID=1000004843",
        "Name": "SJCs Vanilla Face Textures Replacements UPDATE-4559-V2.7z",
        "Size": 86109117,
        "State": {
          "$type": "NexusDownloader, Wabbajack.Lib",
          "Author": "SammyJC",
          "Description": "A simple edit of the vanilla face textures that gives them a more detailed and less blurred appearance.",
          "FileID": 1000004843,
          "GameName": "DragonAgeOrigins",
          "ImageURL": "https://staticdelivery.nexusmods.com/mods/140/images/4559-0-1478194420.png",
          "IsNSFW": false,
          "ModID": 4559,
          "Name": "SJC\u0027s Vanilla Face Textures Replacements",
          "Version": ""
        }
      }
    },
    {
      "Status": "Valid",
      "Original": {
        "Hash": "WgRtk/66BEo=",
        "Meta": "[General]\ngameName=dragonage\nmodID=5125\nfileID=1000006563",
        "Name": "Better Fereldan Kids-5125-1-0-1572637787.7z",
        "Size": 32127,
        "State": {
          "$type": "NexusDownloader, Wabbajack.Lib",
          "Author": "theskymoves",
          "Description": "Adds a variety of appropriate clothing models to children throughout Ferelden. (Requires DarthParametric\u0027s Additional Clothing for Kids!)",
          "FileID": 1000006563,
          "GameName": "DragonAgeOrigins",
          "ImageURL": "https://staticdelivery.nexusmods.com/mods/140/images/5125/5125-1572636263-256732444.jpeg",
          "IsNSFW": false,
          "ModID": 5125,
          "Name": "TSM Better Fereldan Kids",
          "Version": "1.0"
        }
      }
    },
    {
      "Status": "Valid",
      "Original": {
        "Hash": "sQwSZz1ooiI=",
        "Meta": "[General]\ngameName=dragonage\nmodID=2636\nfileID=12858",
        "Name": "DA2DAO-2636.zip",
        "Size": 6853244,
        "State": {
          "$type": "NexusDownloader, Wabbajack.Lib",
          "Author": "hsli",
          "Description": "Bring DA2 Isabela and Flemeth model to DAO",
          "FileID": 12858,
          "GameName": "DragonAgeOrigins",
          "ImageURL": "https://staticdelivery.nexusmods.com/mods/140/images/2636-1-1302453355.jpg",
          "IsNSFW": false,
          "ModID": 2636,
          "Name": "DA2 Isabela and Flemeth to DAO",
          "Version": "0.5"
        }
      }
    },
    {
      "Status": "Valid",
      "Original": {
        "Hash": "vM/ENQRSMVc=",
        "Meta": "[General]\ngameName=dragonage\nmodID=4384\nfileID=1000008594",
        "Name": "Dain\u0027s Fixes-4384-4-2-2-1640325422.zip",
        "Size": 1683580,
        "State": {
          "$type": "NexusDownloader, Wabbajack.Lib",
          "Author": "dainbramage",
          "Description": "A collection of gameplay fixes, tweaks and quality of life changes.",
          "FileID": 1000008594,
          "GameName": "DragonAgeOrigins",
          "ImageURL": null,
          "IsNSFW": false,
          "ModID": 4384,
          "Name": "Dain\u0027s Fixes",
          "Version": "4.2.2"
        }
      }
    },
    {
      "Status": "Valid",
      "Original": {
        "Hash": "rmkNDPTOP1I=",
        "Meta": "[General]\ngameName=dragonage\nmodID=3255\nfileID=16874",
        "Name": "Temporary Chantry Fix-3255-1-0.zip",
        "Size": 361065,
        "State": {
          "$type": "NexusDownloader, Wabbajack.Lib",
          "Author": "NeoKingArthur",
          "Description": "This mod will change all appearances of the Chantry robes into the Dragon Age 2 style. Requires Kirkwall Exports by Amycus.",
          "FileID": 16874,
          "GameName": "DragonAgeOrigins",
          "ImageURL": "https://staticdelivery.nexusmods.com/mods/140/images/3255-1-1323319034.png",
          "IsNSFW": false,
          "ModID": 3255,
          "Name": "Chantry of Ferelden - Robes",
          "Version": "1.0"
        }
      }
    },
    {
      "Status": "Valid",
      "Original": {
        "Hash": "yEJwtnOURGo=",
        "Meta": "[General]\ngameName=dragonage\nmodID=5598\nfileID=1000008541",
        "Name": "Merrill - Vallaslin fix-5598-1-0-1637788434.rar",
        "Size": 33686,
        "State": {
          "$type": "NexusDownloader, Wabbajack.Lib",
          "Author": "AzureWitch",
          "Description": "A new DA2 elves mod that mixes features of the other three existing mods. Requires only Elf Update.",
          "FileID": 1000008541,
          "GameName": "DragonAgeOrigins",
          "ImageURL": "https://staticdelivery.nexusmods.com/mods/140/images/5598/5598-1636833958-1240621150.png",
          "IsNSFW": false,
          "ModID": 5598,
          "Name": "DA2 Elves Triple Mix",
          "Version": "1.0"
        }
      }
    },
    {
      "Status": "Valid",
      "Original": {
        "Hash": "LGJOUih+0Nw=",
        "Meta": "[General]\ngameName=dragonage\nmodID=9\nfileID=206",
        "Name": "NoStartingAbilities_v1_3-9.zip",
        "Size": 11435,
        "State": {
          "$type": "NexusDownloader, Wabbajack.Lib",
          "Author": "jwvanderbeck",
          "Description": "This mod changes new character creation, so that the game will no longer assign certain abilities based on class and background.",
          "FileID": 206,
          "GameName": "DragonAgeOrigins",
          "ImageURL": null,
          "IsNSFW": false,
          "ModID": 9,
          "Name": "No Starting Abilities",
          "Version": "1.3"
        }
      }
    },
    {
      "Status": "Valid",
      "Original": {
        "Hash": "o1iHQCGNu7E=",
        "Meta": "[General]\ngameName=dragonage\nmodID=5636\nfileID=1000008651",
        "Name": "Two Moons in the Sky-5636-1-0-1643157611.zip",
        "Size": 103651,
        "State": {
          "$type": "NexusDownloader, Wabbajack.Lib",
          "Author": "HoneyWhite",
          "Description": "Adds Satina, Thedas\u0027 second moon, to the night sky.",
          "FileID": 1000008651,
          "GameName": "DragonAgeOrigins",
          "ImageURL": "https://staticdelivery.nexusmods.com/mods/140/images/5636/5636-1643196368-1411710775.png",
          "IsNSFW": false,
          "ModID": 5636,
          "Name": "Satina in the Sky",
          "Version": "1.0"
        }
      }
    },
    {
      "Status": "InValid",
      "Original": {
        "Hash": "gJ1VbeHqTG0=",
        "Meta": "[General]\ndirectURL=https://www.moddb.com/downloads/start/110424",
        "Name": "elf_update.7z",
        "Size": 18968038,
        "State": {
          "$type": "ModDBDownloader, Wabbajack.Lib",
          "Url": "https://www.moddb.com/downloads/start/110424"
        }
      }
    },
    {
      "Status": "Valid",
      "Original": {
        "Hash": "HD+v6ch9hE0=",
        "Meta": "[General]\ngameName=dragonage\nmodID=4564\nfileID=1000004706",
        "Name": "Patchy Skin Fix UPDATE-4564-.7z",
        "Size": 851276,
        "State": {
          "$type": "NexusDownloader, Wabbajack.Lib",
          "Author": "SammyJC",
          "Description": "Fixes the ugly, patchy looking skin that occurs when using darker skin tones.",
          "FileID": 1000004706,
          "GameName": "DragonAgeOrigins",
          "ImageURL": "https://staticdelivery.nexusmods.com/mods/140/images/4564-0-1495449806.png",
          "IsNSFW": false,
          "ModID": 4564,
          "Name": "SJC\u0027s Patchy Skin Fix",
          "Version": ""
        }
      }
    },
    {
      "Status": "Valid",
      "Original": {
        "Hash": "YUvLwr5IB6w=",
        "Meta": "[General]\ngameName=dragonage\nmodID=4564\nfileID=1000004083",
        "Name": "SJC\u0027s Patchy Skin Fix-4564-.zip",
        "Size": 2253609,
        "State": {
          "$type": "NexusDownloader, Wabbajack.Lib",
          "Author": "SammyJC",
          "Description": "Fixes the ugly, patchy looking skin that occurs when using darker skin tones.",
          "FileID": 1000004083,
          "GameName": "DragonAgeOrigins",
          "ImageURL": "https://staticdelivery.nexusmods.com/mods/140/images/4564-0-1495449806.png",
          "IsNSFW": false,
          "ModID": 4564,
          "Name": "SJC\u0027s Patchy Skin Fix",
          "Version": ""
        }
      }
    },
    {
      "Status": "Valid",
      "Original": {
        "Hash": "ycSJyDomIjs=",
        "Meta": "[General]\ngameName=dragonage\nmodID=4689\nfileID=1000006801",
        "Name": "QUDAO Hotfix v3_52-4689-3-52-1582914537.7z",
        "Size": 433721,
        "State": {
          "$type": "NexusDownloader, Wabbajack.Lib",
          "Author": "Qwinn",
          "Description": "New workaround hotfix for the rare but dreaded Skin Deep/Dereliction of Duty/Scrolls of Banastor bug.  You should install even if it hasn\u0027t affected you yet! This fixpack attempts to address ALL dialogue, quest, scripting, plot, and most item bugs in the base game of Dragon Age: Origins.  It also restores much previously inaccessible content.",
          "FileID": 1000006801,
          "GameName": "DragonAgeOrigins",
          "ImageURL": "https://staticdelivery.nexusmods.com/mods/140/images/4689-0-1497207820.png",
          "IsNSFW": false,
          "ModID": 4689,
          "Name": "Qwinn\u0027s Ultimate DAO Fixpack v3.52",
          "Version": "3.52"
        }
      }
    },
    {
      "Status": "Valid",
      "Original": {
        "Hash": "nRr0hT4wcRg=",
        "Meta": "[General]\ngameName=dragonage\nmodID=5625\nfileID=1000008611",
        "Name": "Retexturing DAO Fixes-5625-1-0-1640792539.rar",
        "Size": 11442391,
        "State": {
          "$type": "NexusDownloader, Wabbajack.Lib",
          "Author": "kikokoalas",
          "Description": "A compilation of various small mods I\u0027ve made that I didn\u0027t deem big enough for their own page.",
          "FileID": 1000008611,
          "GameName": "DragonAgeOrigins",
          "ImageURL": "https://staticdelivery.nexusmods.com/mods/140/images/5625/5625-1640758846-476982515.png",
          "IsNSFW": false,
          "ModID": 5625,
          "Name": "The Deck of Many Mods",
          "Version": "1.0"
        }
      }
    },
    {
      "Status": "Valid",
      "Original": {
        "Hash": "UD6J4QL1/m8=",
        "Meta": "[General]\ngameName=dragonage\nmodID=1112\nfileID=5574",
        "Name": "Blackblade Drop Fix-1112.7z",
        "Size": 586,
        "State": {
          "$type": "NexusDownloader, Wabbajack.Lib",
          "Author": "Schwinni",
          "Description": "Fixes the bug in Awakening that the High Dragon in the Dragonbone Wastes doesn\\\u0027t drop the Blackblade Gloves and Boots.",
          "FileID": 5574,
          "GameName": "DragonAgeOrigins",
          "ImageURL": "https://staticdelivery.nexusmods.com/mods/140/images/1112-1-1271872273.jpg",
          "IsNSFW": false,
          "ModID": 1112,
          "Name": "Awakening Blackblade Armor Dragon Drop Fix",
          "Version": "1.0"
        }
      }
    },
    {
      "Status": "Valid",
      "Original": {
        "Hash": "WcLEsWUUbxI=",
        "Meta": "[General]\ngameName=dragonage\nmodID=122\nfileID=9571",
        "Name": "Compatibility Patch for FtG Scaled UI Mod-122.zip",
        "Size": 84793,
        "State": {
          "$type": "NexusDownloader, Wabbajack.Lib",
          "Author": "Phaenan",
          "Description": "Fully customize your party equipement through a new craftskill allowing you to imbue your items with any magical property you desire, and through new skills allowing all kind of items modification : name, material, model, icon, visual effect, itemset... Fully customizable via an in-game configuration menu : Whether TWF is balanced or not is your ch",
          "FileID": 9571,
          "GameName": "DragonAgeOrigins",
          "ImageURL": "https://staticdelivery.nexusmods.com/mods/140/images/122-1-1289350188.jpg",
          "IsNSFW": false,
          "ModID": 122,
          "Name": "The Winter Forge",
          "Version": "1.0.4"
        }
      }
    },
    {
      "Status": "Valid",
      "Original": {
        "Hash": "9+SB9ILaAWM=",
        "Meta": "[General]\ngameName=dragonage\nmodID=5598\nfileID=1000009392",
        "Name": "Tranquil Elves with Brands-5598-1-0-1666657466.rar",
        "Size": 50567,
        "State": {
          "$type": "NexusDownloader, Wabbajack.Lib",
          "Author": "AzureWitch",
          "Description": "A new DA2 elves mod that mixes features of the other three existing mods. Requires only Elf Update.",
          "FileID": 1000009392,
          "GameName": "DragonAgeOrigins",
          "ImageURL": "https://staticdelivery.nexusmods.com/mods/140/images/5598/5598-1636833958-1240621150.png",
          "IsNSFW": false,
          "ModID": 5598,
          "Name": "DA2 Elves Triple Mix",
          "Version": "1.0"
        }
      }
    },
    {
      "Status": "Valid",
      "Original": {
        "Hash": "j7nSUeKW6qo=",
        "Meta": "[General]\ngameName=dragonage\nmodID=4462\nfileID=1000003564",
        "Name": "JB3textures-4462-1-0.zip",
        "Size": 16301205,
        "State": {
          "$type": "NexusDownloader, Wabbajack.Lib",
          "Author": "magpiedragon",
          "Description": "Replaces vanilla meshes for Medium and Heavy female armors for all races with more unisex ones. Includes edited armor textures to match. No more boobplate.",
          "FileID": 1000003564,
          "GameName": "DragonAgeOrigins",
          "ImageURL": "https://staticdelivery.nexusmods.com/mods/140/images/4462-0-1462355101.jpg",
          "IsNSFW": false,
          "ModID": 4462,
          "Name": "Neutral Female Armor (Medium and Heavy edition)",
          "Version": "1.1"
        }
      }
    },
    {
      "Status": "Valid",
      "Original": {
        "Hash": "rBdbTeTh4eA=",
        "Meta": "[General]\ngameName=dragonage\nmodID=3253\nfileID=16933",
        "Name": "Tranquil Brand - By Dracomies-3253.zip",
        "Size": 677944,
        "State": {
          "$type": "NexusDownloader, Wabbajack.Lib",
          "Author": "NeoKingArthur",
          "Description": "This mod will change the appearance of all Circle Mage Robes from the weird looking model into the clean more elegant model of First Enchanter Irving\u0027s robe style.",
          "FileID": 16933,
          "GameName": "DragonAgeOrigins",
          "ImageURL": "https://staticdelivery.nexusmods.com/mods/140/images/3253-1-1323318200.png",
          "IsNSFW": false,
          "ModID": 3253,
          "Name": "Mages of Ferelden",
          "Version": "1.0"
        }
      }
    },
    {
      "Status": "Valid",
      "Original": {
        "Hash": "5gqL4Xx/lAA=",
        "Meta": "[General]\ngameName=dragonage\nmodID=5287\nfileID=1000011644",
        "Name": "Awakening Lore-Friendly Epilogue Rewrite-5287-1-2-1719791002.zip",
        "Size": 21483,
        "State": {
          "$type": "NexusDownloader, Wabbajack.Lib",
          "Author": "mintflavoredwindows",
          "Description": "A rewrite of the Awakening epilogue slideshow that attempts to stop it from conflicting with events and lore established in later games, along with implementing bugfixes and some new content for player choices that the developers overlooked",
          "FileID": 1000011644,
          "GameName": "DragonAgeOrigins",
          "ImageURL": "https://staticdelivery.nexusmods.com/mods/140/images/5287/5287-1593813541-1891487194.jpeg",
          "IsNSFW": false,
          "ModID": 5287,
          "Name": "Awakening Lore-Friendly Epilogue Rewrite",
          "Version": "1.0"
        }
      }
    },
    {
      "Status": "Valid",
      "Original": {
        "Hash": "nsqdApdY38Q=",
        "Meta": "[General]\ngameName=dragonage\nmodID=3328\nfileID=17310",
        "Name": "DA2 Merrill and Marethari-3328-1-0.rar",
        "Size": 53960,
        "State": {
          "$type": "NexusDownloader, Wabbajack.Lib",
          "Author": "incendiaire",
          "Description": "This mod will replace Merrill and Keeper Marethari from the Dalish origin story with versions that more closely resemble their DA2 counterparts, for the sake of visual continuity.",
          "FileID": 17310,
          "GameName": "DragonAgeOrigins",
          "ImageURL": "https://staticdelivery.nexusmods.com/mods/140/images/3328-1-1325611107.jpg",
          "IsNSFW": false,
          "ModID": 3328,
          "Name": "DA2 Merrill and Marethari for DAO",
          "Version": "1.0"
        }
      }
    },
    {
      "Status": "Valid",
      "Original": {
        "Hash": "HFhbNkjWjow=",
        "Meta": "[General]\ngameName=dragonage\nmodID=4559\nfileID=1000004126",
        "Name": "SJCs Vanilla Face Textures Replacements JUSTICE SKIN-4559-.zip",
        "Size": 4070084,
        "State": {
          "$type": "NexusDownloader, Wabbajack.Lib",
          "Author": "SammyJC",
          "Description": "A simple edit of the vanilla face textures that gives them a more detailed and less blurred appearance.",
          "FileID": 1000004126,
          "GameName": "DragonAgeOrigins",
          "ImageURL": "https://staticdelivery.nexusmods.com/mods/140/images/4559-0-1478194420.png",
          "IsNSFW": false,
          "ModID": 4559,
          "Name": "SJC\u0027s Vanilla Face Textures Replacements",
          "Version": ""
        }
      }
    },
    {
      "Status": "Valid",
      "Original": {
        "Hash": "6792G9FxQNU=",
        "Meta": "[General]\ngameName=dragonage\nmodID=5598\nfileID=1000009394",
        "Name": "Fixed UTC Files-5598-1-0-1666730500.rar",
        "Size": 10362,
        "State": {
          "$type": "NexusDownloader, Wabbajack.Lib",
          "Author": "AzureWitch",
          "Description": "A new DA2 elves mod that mixes features of the other three existing mods. Requires only Elf Update.",
          "FileID": 1000009394,
          "GameName": "DragonAgeOrigins",
          "ImageURL": "https://staticdelivery.nexusmods.com/mods/140/images/5598/5598-1636833958-1240621150.png",
          "IsNSFW": false,
          "ModID": 5598,
          "Name": "DA2 Elves Triple Mix",
          "Version": "1.0"
        }
      }
    },
    {
      "Status": "Valid",
      "Original": {
        "Hash": "kl7r8FM4o/w=",
        "Meta": "[General]\ngameName=dragonage\nmodID=122\nfileID=16894",
        "Name": "TWF 1-04 fix1-122-1.zip",
        "Size": 106028,
        "State": {
          "$type": "NexusDownloader, Wabbajack.Lib",
          "Author": "Phaenan",
          "Description": "Fully customize your party equipement through a new craftskill allowing you to imbue your items with any magical property you desire, and through new skills allowing all kind of items modification : name, material, model, icon, visual effect, itemset... Fully customizable via an in-game configuration menu : Whether TWF is balanced or not is your ch",
          "FileID": 16894,
          "GameName": "DragonAgeOrigins",
          "ImageURL": "https://staticdelivery.nexusmods.com/mods/140/images/122-1-1289350188.jpg",
          "IsNSFW": false,
          "ModID": 122,
          "Name": "The Winter Forge",
          "Version": "1.0.4"
        }
      }
    },
    {
      "Status": "Valid",
      "Original": {
        "Hash": "LwEcXsH8H9s=",
        "Meta": "[General]\ngameName=dragonage\nmodID=181\nfileID=6942",
        "Name": "Advanced Tactics 31-181.dazip",
        "Size": 119432,
        "State": {
          "$type": "NexusDownloader, Wabbajack.Lib",
          "Author": "Anakin",
          "Description": "This add-in fix various bugs in tactics system, party members behaviors and AI.\r\n\r\nIt enable new conditions and actions in the tactics system that give you the opportunity to configure your followers more precisely.\r\n\r\nIt also fix some bugs that players may encounter during combat. Full list of fixes available in long description.",
          "FileID": 6942,
          "GameName": "DragonAgeOrigins",
          "ImageURL": "https://staticdelivery.nexusmods.com/mods/140/images/181-1-1266876602.png",
          "IsNSFW": false,
          "ModID": 181,
          "Name": "Advanced Tactics",
          "Version": "3.1"
        }
      }
    },
    {
      "Status": "Valid",
      "Original": {
        "Hash": "/09JPKX+eAs=",
        "Meta": "[General]\ngameName=dragonage\nmodID=73\nfileID=7837",
        "Name": "FtG UI Mod - v2-1-73.zip",
        "Size": 6876443,
        "State": {
          "$type": "NexusDownloader, Wabbajack.Lib",
          "Author": "FollowTheGourd",
          "Description": "Readability improvements for cutscenes, the quest journal, the codex, conversation history, tooltips, the inventory, and other various menus. There\\\u0027s still lots more to go and more versions to come.",
          "FileID": 7837,
          "GameName": "DragonAgeOrigins",
          "ImageURL": "https://staticdelivery.nexusmods.com/mods/140/images/73-1-1263453338.jpg",
          "IsNSFW": false,
          "ModID": 73,
          "Name": "FtG UI Mod - More Readable Fonts and UI",
          "Version": "v2.1"
        }
      }
    },
    {
      "Status": "Valid",
      "Original": {
        "Hash": "XGXA23/stKE=",
        "Meta": "[General]\ngameName=dragonage\nmodID=1762\nfileID=9012",
        "Name": "SilveriteFix_v102-1762.rar",
        "Size": 7683,
        "State": {
          "$type": "NexusDownloader, Wabbajack.Lib",
          "Author": "Terra_Ex",
          "Description": "This mod fixes the infamous Silverite Mines equipment glitch that causes you to permanently lose some/all of the equipment on your player character. With this fix installed the scene involving the Architect \u0026 Utha will display correctly (not against a black backdrop) and your equipment will be correctly removed at the appropriate time.  ",
          "FileID": 9012,
          "GameName": "DragonAgeOrigins",
          "ImageURL": "https://staticdelivery.nexusmods.com/mods/140/images/1762-1-1285942889.jpg",
          "IsNSFW": false,
          "ModID": 1762,
          "Name": "Awakening Silverite Mines Bugfix",
          "Version": "1.0.2"
        }
      }
    },
    {
      "Status": "Valid",
      "Original": {
        "Hash": "v0spU2glqZY=",
        "Meta": "[General]\ngameName=dragonage\nmodID=14\nfileID=359",
        "Name": "Character Respec Mod v1_6-14.dazip",
        "Size": 33795,
        "State": {
          "$type": "NexusDownloader, Wabbajack.Lib",
          "Author": "Peter Kovacs",
          "Description": "Allows the player to reset the attribute, specialization, spell, talent and skill points of any party members.",
          "FileID": 359,
          "GameName": "DragonAgeOrigins",
          "ImageURL": "https://staticdelivery.nexusmods.com/mods/140/images/14-2-1258361655.jpg",
          "IsNSFW": false,
          "ModID": 14,
          "Name": "Character Respecialization",
          "Version": "1.6"
        }
      }
    },
    {
      "Status": "Valid",
      "Original": {
        "Hash": "X2WUBg6vndo=",
        "Meta": "[General]\ngameName=dragonage\nmodID=2784\nfileID=13652",
        "Name": "FtG_Quickbar-2784.zip",
        "Size": 314160,
        "State": {
          "$type": "NexusDownloader, Wabbajack.Lib",
          "Author": "FollowTheGourd",
          "Description": "Use up to all fifty quickslots regardless of display resolution. Multiple rows. Row centering options.",
          "FileID": 13652,
          "GameName": "DragonAgeOrigins",
          "ImageURL": "https://staticdelivery.nexusmods.com/mods/140/images/2784-1-1304835137.jpg",
          "IsNSFW": false,
          "ModID": 2784,
          "Name": "FtG Quickbar - Center and Multi Rows",
          "Version": "v1.0"
        }
      }
    },
    {
      "Status": "Valid",
      "Original": {
        "Hash": "kuFgg+EiZwU=",
        "Meta": "[General]\ngameName=dragonage\nmodID=3924\nfileID=1000001654",
        "Name": "HD Stbl-presets 1_2-3924-1-2.7z",
        "Size": 1951864,
        "State": {
          "$type": "NexusDownloader, Wabbajack.Lib",
          "Author": "ViLiSSa",
          "Description": "HD (2048x2048) replacer for default presets",
          "FileID": 1000001654,
          "GameName": "DragonAgeOrigins",
          "ImageURL": "https://staticdelivery.nexusmods.com/mods/140/images/3924-1-1381082745.jpg",
          "IsNSFW": false,
          "ModID": 3924,
          "Name": "HD Eyebrow and Stubble presets",
          "Version": "1.2"
        }
      }
    },
    {
      "Status": "Valid",
      "Original": {
        "Hash": "M3oMF/zLJRE=",
        "Meta": "[General]\ngameName=dragonage\nmodID=3258\nfileID=17150",
        "Name": "Core Mod GWoF - REQUIRED-3258-2-5.dazip",
        "Size": 43220881,
        "State": {
          "$type": "NexusDownloader, Wabbajack.Lib",
          "Author": "NeoKingArthur",
          "Description": "This mod will give you DA2 style Grey Warden armors and weapons for DA:O. This mod also changes the appearances of all Grey Warden NPCs into wearing a uniform Grey Warden armors.",
          "FileID": 17150,
          "GameName": "DragonAgeOrigins",
          "ImageURL": "https://staticdelivery.nexusmods.com/mods/140/images/3258-1-1323317032.png",
          "IsNSFW": false,
          "ModID": 3258,
          "Name": "Grey Wardens of Ferelden",
          "Version": "2.5"
        }
      }
    },
    {
      "Status": "Valid",
      "Original": {
        "Hash": "+5Gv/kvq36Y=",
        "Meta": "[General]\ngameName=dragonage\nmodID=3098\nfileID=1000000460",
        "Name": "Kirkwall Exports-3098-2-17.rar",
        "Size": 72631562,
        "State": {
          "$type": "NexusDownloader, Wabbajack.Lib",
          "Author": "Amycus",
          "Description": "Adds armor and weapons from DA2 to DA:O",
          "FileID": 1000000460,
          "GameName": "DragonAgeOrigins",
          "ImageURL": "https://staticdelivery.nexusmods.com/mods/140/images/3098-1-1364765092.jpg",
          "IsNSFW": false,
          "ModID": 3098,
          "Name": "Kirkwall Exports",
          "Version": "2.17"
        }
      }
    },
    {
      "Status": "Valid",
      "Original": {
        "Hash": "AtUxHzoa420=",
        "Meta": "[General]\ngameName=dragonage\nmodID=5800\nfileID=1000009130",
        "Name": "Reshade Preset-5800-1a-1659162988.zip",
        "Size": 678,
        "State": {
          "$type": "NexusDownloader, Wabbajack.Lib",
          "Author": "Craftian",
          "Description": "Say goodbye to all those blurry smears with a HD texture pack, upscaled by AI. Includes optional Reshade preset.",
          "FileID": 1000009130,
          "GameName": "DragonAgeOrigins",
          "ImageURL": "https://staticdelivery.nexusmods.com/mods/140/images/5800/5800-1659161508-1916136843.png",
          "IsNSFW": false,
          "ModID": 5800,
          "Name": "Old Gods",
          "Version": "1.0"
        }
      }
    },
    {
      "Status": "Valid",
      "Original": {
        "Hash": "tf8x6+y5MLc=",
        "Meta": "[General]\ngameName=dragonage\nmodID=4689\nfileID=1000006176",
        "Name": "QUDAO Fixpack v3.5-4689-3-5-1550475932.zip",
        "Size": 131278988,
        "State": {
          "$type": "NexusDownloader, Wabbajack.Lib",
          "Author": "Qwinn",
          "Description": "New workaround hotfix for the rare but dreaded Skin Deep/Dereliction of Duty/Scrolls of Banastor bug.  You should install even if it hasn\u0027t affected you yet! This fixpack attempts to address ALL dialogue, quest, scripting, plot, and most item bugs in the base game of Dragon Age: Origins.  It also restores much previously inaccessible content.",
          "FileID": 1000006176,
          "GameName": "DragonAgeOrigins",
          "ImageURL": "https://staticdelivery.nexusmods.com/mods/140/images/4689-0-1497207820.png",
          "IsNSFW": false,
          "ModID": 4689,
          "Name": "Qwinn\u0027s Ultimate DAO Fixpack v3.52",
          "Version": "3.52"
        }
      }
    },
    {
      "Status": "InValid",
      "Original": {
        "Hash": "bE91h/Uu+RE=",
        "Meta": "[General]\ndirectURL=https://www.moddb.com/downloads/start/173155",
        "Name": "qunari_update.7z",
        "Size": 11435946,
        "State": {
          "$type": "ModDBDownloader, Wabbajack.Lib",
          "Url": "https://www.moddb.com/downloads/start/173155"
        }
      }
    },
    {
      "Status": "Valid",
      "Original": {
        "Hash": "rEaQw6PpUqg=",
        "Meta": "[General]\ngameName=dragonage\nmodID=5035\nfileID=1000006213",
        "Name": "Dalish Armor Replacement-5035-1-1552089884.7z",
        "Size": 1447,
        "State": {
          "$type": "NexusDownloader, Wabbajack.Lib",
          "Author": "yixura",
          "Description": "Replaces default dalish armor models with new set.",
          "FileID": 1000006213,
          "GameName": "DragonAgeOrigins",
          "ImageURL": "https://staticdelivery.nexusmods.com/mods/140/images/5035/5035-1552089736-181999572.png",
          "IsNSFW": false,
          "ModID": 5035,
          "Name": "Dalish Armor Replacement",
          "Version": "1"
        }
      }
    },
    {
      "Status": "Valid",
      "Original": {
        "Hash": "oTnoFgjjjy0=",
        "Meta": "[General]\ngameName=dragonage\nmodID=4981\nfileID=1000006097",
        "Name": "Lore-Friendly Epilogue Rewrite-4981-1-0-1545030575.zip",
        "Size": 37772,
        "State": {
          "$type": "NexusDownloader, Wabbajack.Lib",
          "Author": "mintflavoredwindows",
          "Description": "Rewrites a bunch of epilogue slides so that they no longer contradict later installments in the series, while also fixing some bugs and adding new slides for a handful of conditions that were overlooked in the vanilla epilogue",
          "FileID": 1000006097,
          "GameName": "DragonAgeOrigins",
          "ImageURL": "https://staticdelivery.nexusmods.com/mods/140/images/4981/4981-1545029905-1443346454.jpeg",
          "IsNSFW": false,
          "ModID": 4981,
          "Name": "Lore-Friendly Epilogue Rewrite",
          "Version": "1.0"
        }
      }
    },
    {
      "Status": "Valid",
      "Original": {
        "Hash": "q+SnAgpCUZ0=",
        "Meta": "[General]\ngameName=dragonage\nmodID=122\nfileID=10762",
        "Name": "Lastest release-122-1-0-4.zip",
        "Size": 14365711,
        "State": {
          "$type": "NexusDownloader, Wabbajack.Lib",
          "Author": "Phaenan",
          "Description": "Fully customize your party equipement through a new craftskill allowing you to imbue your items with any magical property you desire, and through new skills allowing all kind of items modification : name, material, model, icon, visual effect, itemset... Fully customizable via an in-game configuration menu : Whether TWF is balanced or not is your ch",
          "FileID": 10762,
          "GameName": "DragonAgeOrigins",
          "ImageURL": "https://staticdelivery.nexusmods.com/mods/140/images/122-1-1289350188.jpg",
          "IsNSFW": false,
          "ModID": 122,
          "Name": "The Winter Forge",
          "Version": "1.0.4"
        }
      }
    },
    {
      "Status": "Valid",
      "Original": {
        "Hash": "UC40eOS4YFA=",
        "Meta": "[General]\ngameName=dragonage\nmodID=664\nfileID=3572",
        "Name": "dao_extradogslot_1_41-664.dazip",
        "Size": 55569,
        "State": {
          "$type": "NexusDownloader, Wabbajack.Lib",
          "Author": "Dheuster",
          "Description": "Allows you to make your pet mabari war dog a permanent 5th travelling companion. ",
          "FileID": 3572,
          "GameName": "DragonAgeOrigins",
          "ImageURL": "https://staticdelivery.nexusmods.com/mods/140/images/664-1-1264560138.jpg",
          "IsNSFW": false,
          "ModID": 664,
          "Name": "Extra Dog Slot",
          "Version": "1.41"
        }
      }
    },
    {
      "Status": "Valid",
      "Original": {
        "Hash": "dU7uRi/ECbA=",
        "Meta": "[General]\ngameName=dragonage\nmodID=301\nfileID=7055",
        "Name": "Lock Bash v7e for Original and Awakening-301.7z",
        "Size": 14463,
        "State": {
          "$type": "NexusDownloader, Wabbajack.Lib",
          "Author": "xatmos",
          "Description": "Works with Awakening! Bash open locked chests and doors. The way the game should have been.",
          "FileID": 7055,
          "GameName": "DragonAgeOrigins",
          "ImageURL": "https://staticdelivery.nexusmods.com/mods/140/images/301-1-1260737774.jpg",
          "IsNSFW": false,
          "ModID": 301,
          "Name": "Lock Bash",
          "Version": "7"
        }
      }
    }
  ],
  "Status": "Failed",
  "Failures": 3,
  "SmallImage": "https://raw.githubusercontent.com/wabbajack-tools/mod-lists/master/reports/HoS/YotB_small.webp",
  "LargeImage": "https://raw.githubusercontent.com/wabbajack-tools/mod-lists/master/reports/HoS/YotB_large.webp"
}